helperpy/__init__.py
helperpy/asynchronous/__init__.py
helperpy/asynchronous/async_utils.py
helperpy/core/__init__.py
helperpy/core/date_ops.py
helperpy/core/decorators.py
helperpy/core/email_ops.py
helperpy/core/excel_ops.py
helperpy/core/exceptions.py
helperpy/core/file_io.py
helperpy/core/logging_ops.py
helperpy/core/mathematics.py
helperpy/core/query_ops.py
helperpy/core/random_data_generator.py
helperpy/core/string_ops.py
helperpy/core/text_casing.py
helperpy/core/type_annotations.py
helperpy/core/utils.py
helperpy/data_viz/__init__.py
helperpy/data_viz/utils.py
helperpy/data_wrangler/__init__.py
helperpy/data_wrangler/explore.py
helperpy/data_wrangler/transform.py
helperpy/frameworks/__init__.py
helperpy/frameworks/django_ops/__init__.py
helperpy/frameworks/django_ops/decorators.py
helperpy/frameworks/django_ops/utils.py
helperpy-0.0.4.dist-info/LICENSE
helperpy-0.0.4.dist-info/METADATA
helperpy-0.0.4.dist-info/WHEEL
helperpy-0.0.4.dist-info/top_level.txt
helperpy-0.0.4.dist-info/RECORD
